{
	"exercises": [
		{

			"name": "Oblique twist",
			"video": "https://vimeo.com/178079508"
		},
		{

			"name": "Benchpress",
			"video": "https://vimeo.com/178057019"
		},
		{

			"name": "Deadlift",
			"video": "https://vimeo.com/178056325"
		},
		{

			"name": "Squat",
			"video": "https://vimeo.com/178056008"
		},
		{

			"name": "Tricep pulldown",
			"video": "https://vimeo.com/178054967"
		},
		{

			"name": "Pulley crunch",
			"video": "https://vimeo.com/178052126"
		},
		{

			"name": "Floor crunch",
			"video": "https://vimeo.com/178050912"
		},
		{

			"name": "Overhead tricep extension",
			"video": "https://vimeo.com/178050262"
		},
		{

			"name": "Dumbbell press",
			"video": "https://vimeo.com/178048727"
		},
		{

			"name": "Forearm curl back (15 reps)",
			"video": "https://vimeo.com/178047269"
		},
		{

			"name": "Forearm curl in (15 reps)",
			"video": "https://vimeo.com/178047269"
		},
		{

			"name": "Seated pulley row",
			"video": "https://vimeo.com/178042607"
		},
		{

			"name": "Shrug",
			"video": "https://vimeo.com/177971664"
		},
		{

			"name": "Calf raise",
			"video": "https://vimeo.com/177971348"
		},
		{

			"name": "Dumbbell romanian deadlift",
			"video": "https://vimeo.com/177971032"
		},
		{

			"name": "Forearm curl up (25 reps)",
			"video": "https://vimeo.com/177970644"
		},
		{

			"name": "Dumbbell squat",
			"video": "https://vimeo.com/177970342"
		},
		{

			"name": "Front raise",
			"video": "https://vimeo.com/177969758"
		},
		{

			"name": "Julian tricep extension",
			"video": "https://vimeo.com/177969524"
		},
		{

			"name": "Bicep curl",
			"video": "https://vimeo.com/177968823"
		},
		{

			"name": "Dumbbell incline press",
			"video": "https://vimeo.com/177967959"
		},
		{

			"name": "Hammer pulley curls 2h",
			"video": "https://vimeo.com/"
		},
		{

			"name": "Side raise",
			"video": "https://vimeo.com/177961354"
		},
		{

			"name": "Hand grippers",
			"video": "https://vimeo.com/177766222"
		},
		{

			"name": "Dumbbell shoulder press",
			"video": "https://www.vimeo.com/151248907"
		},
		{

			"name": "Overhead press",
			"video": "https://vimeo.com/96081016"
		},
		{

			"name": "Hamstring curl",
			"video": "https://vimeo.com/164443477"
		},
		{

			"name": "Lat pulldown",
			"video": "https://vimeo.com/164080300"
		},
		{

			"name": "Hanging leg raise",
			"video": "https://vimeo.com/39560703"
		}
	]
}
